README.rst
setup.py
cf_s3field/__init__.py
cf_s3field/fields.py
cf_s3field/files.py
cf_s3field.egg-info/PKG-INFO
cf_s3field.egg-info/SOURCES.txt
cf_s3field.egg-info/dependency_links.txt
cf_s3field.egg-info/pbr.json
cf_s3field.egg-info/requires.txt
cf_s3field.egg-info/top_level.txt
cf_s3field.egg-info/zip-safe