Metadata-Version: 1.1
Name: cf-s3field
Version: 0.0.2
Summary: S3 fields to upload images to s3 instead of file system
Home-page: UNKNOWN
Author: Hitul Mistry
Author-email: UNKNOWN
License: UNKNOWN
Keywords: Django,s3field,coverfox,cf_s3_field
Platform: UNKNOWN
Classifier: Intended Audience :: Developers
Classifier: Natural Language :: English
Classifier: Operating System :: OS Independent
Classifier: Operating System :: POSIX :: Linux
Classifier: Operating System :: Microsoft :: Windows
Classifier: Operating System :: MacOS :: MacOS X
Classifier: Programming Language :: Python
Classifier: Programming Language :: Python :: 2
Classifier: Programming Language :: Python :: 2.7
Classifier: Programming Language :: Python :: Implementation :: CPython
Classifier: Topic :: Software Development
